examples/__init__.py
examples/extract.py
examples/generate_mrt_json.py
examples/run_evaluations.py
examples/run_recommending.py
examples/test_mrt.py
mrtframework/__init__.py
mrtframework/master_reading_tree.py
mrtframework/reading.py
mrtframework/reasoning.py
mrtframework/recommending.py
mrtframework/retrieving.py
mrtframework/roadmapping.py
mrtframework/utils.py
mrtframework/algorithms/__init__.py
mrtframework/algorithms/automatic_labeling.py
mrtframework/algorithms/kernel_kmeans.py
mrtframework/algorithms/kernel_kmeans_old.py
mrtframework/algorithms/prone.py
mrtframework/base/__init__.py
mrtframework/base/cluster.py
mrtframework/base/publication.py
mrtframework/data_provider/__init__.py
mrtframework/data_provider/data_provider.py
mrtframework/data_provider/downloader.py
mrtframework/data_provider/exceptions.py
mrtframework/data_provider/utils.py
mrtframework/evaluations/__init__.py
mrtframework/evaluations/comention_benchmark.py
mrtframework/evaluations/mst_benchmark.py
mrtframework/evaluations/neighborhood_similarity_benchmark.py
mrtframework-0.2.1.dist-info/METADATA
mrtframework-0.2.1.dist-info/WHEEL
mrtframework-0.2.1.dist-info/top_level.txt
mrtframework-0.2.1.dist-info/RECORD
