Metadata-Version: 2.1
Name: mrtframework
Version: 0.2.1
Summary: The MRT framework to generate evolution roadmap for publications.
Home-page: https://github.com/THUDM/mrt
Author: Da Yin, Weng Lam Tam, Ming Ding, Jie Tang
Author-email: yd18@mails.tsinghua.edu.cn, tanyl19@mails.tsinghua.edu.cn, dm18@mails.tsinghua.edu.cn, jietang@tsinghua.edu.cn
License: MIT
Download-URL: https://github.com/THUDM/mrtframework/archive/0.2.0.tar.gz
Keywords: data mining,information retrieval,document representation,network embedding,document clustering
Platform: UNKNOWN
Classifier: Development Status :: 3 - Alpha
Classifier: Intended Audience :: Science/Research
Classifier: Topic :: Scientific/Engineering :: Artificial Intelligence
Classifier: License :: OSI Approved :: MIT License
Classifier: Programming Language :: Python :: 3
Classifier: Programming Language :: Python :: 3.5
Classifier: Programming Language :: Python :: 3.6
Classifier: Programming Language :: Python :: 3.7
Requires-Dist: networkx
Requires-Dist: requests
Requires-Dist: tqdm
Requires-Dist: pymongo
Requires-Dist: node2vec
Requires-Dist: nltk
Requires-Dist: numpy
Requires-Dist: pyssdb
Requires-Dist: torch
Requires-Dist: retry
Requires-Dist: scipy
Requires-Dist: pick
Requires-Dist: scikit-learn
Requires-Dist: sentence-transformers
